Metadata-Version: 2.2
Name: CCTV_detector_new
Version: 0.1.0
Summary: CCTV Intelligent Detection System based on YOLOv8
Home-page: https://github.com/cctv-detector/CCTV_detector_new
Author: CCTV Development Team
Author-email: CCTV Development Team <info@cctv-detector.com>
License: MIT
Project-URL: Homepage, https://github.com/cctv-detector/CCTV_detector_new
Project-URL: Bug Tracker, https://github.com/cctv-detector/CCTV_detector_new/issues
Classifier: Programming Language :: Python :: 3
Classifier: License :: OSI Approved :: MIT License
Classifier: Operating System :: OS Independent
Requires-Python: >=3.8
Dynamic: author
Dynamic: home-page
Dynamic: requires-python
